snaplit-0.1.0.dist-info/METADATA
snaplit-0.1.0.dist-info/WHEEL
snaplit-0.1.0.dist-info/licenses/LICENSE
snaplit/__init__.py
snaplit/_rust_snaplit.cpython-311-darwin.so
snaplit/graph/__init__.py
snaplit/graph/py_basegraph.py
snaplit/graph/py_digraph.py
snaplit/graph/py_hypergraph.py
snaplit/graph/py_weighted_digraph.py
snaplit/graph/py_weighted_graph.py
snaplit/hashing/__init__.py
snaplit/hashing/py_rhoodmap.py
snaplit/hashing/py_snapmap.py
snaplit/linear/__init__.py
snaplit/linear/py_arraystack.py
snaplit/linear/py_circularbuffer.py
snaplit/linear/py_linked_list.py
snaplit/linear/py_priority_queue.py
snaplit/linear/py_queue.py
snaplit/linear/py_ringbuffer.py
snaplit/linear/py_stack.py
snaplit/probability/__init__.py
snaplit/probability/py_bloom_filter.py
snaplit/probability/py_cuckoo_filter.py
snaplit/probability/py_flatlist.py
snaplit/trees/__init__.py
snaplit/trees/py_avl_tree.py
snaplit/trees/py_binary_tree.py
snaplit/trees/py_trie.py
snaplit-0.1.0.dist-info/RECORD
