Metadata-Version: 2.4
Name: snaplit
Version: 0.1.0
Classifier: Programming Language :: Rust
Classifier: Programming Language :: Python :: 3
Classifier: Programming Language :: Python :: Implementation :: CPython
Classifier: Programming Language :: Python :: Implementation :: PyPy
Classifier: Topic :: Software Development :: Libraries
Classifier: Topic :: Software Development :: Libraries :: Python Modules
License-File: LICENSE
Summary: Snaplit — a Rust-powered Python package
Keywords: rust,py03,python-extensions,data-structures,graphs,linear,probability,trees,hashing,algorithm,performance,library,ffi
Author-email: HysingerDev <HysingerDev@gmail.com>
Requires-Python: >=3.8
